{
    "cca2": "CM",
    "requirements": {
        "Bolivia": [
            "a",
            "90 days"
        ],
        "Botswana": [
            "f",
            "90 days"
        ],
        "Burundi": [
            "a",
            "30 days; obtainable at Bujumbura International Airport"
        ],
        "Cape Verde": [
            "a",
            ""
        ],
        "Central African Republic": [
            "f",
            ""
        ],
        "Chad": [
            "f",
            ""
        ],
        "Comoros": [
            "a",
            ""
        ],
        "Djibouti": [
            "a",
            ""
        ],
        "Dominica": [
            "f",
            "21 days"
        ],
        "Ecuador": [
            "f",
            "90 days"
        ],
        "Georgia": [
            "a",
            ""
        ],
        "Grenada": [
            "f",
            ""
        ],
        "Guinea-Bissau": [
            "a",
            "90 days"
        ],
        "Haiti": [
            "f",
            "3 months"
        ],
        "Lesotho": [
            "f",
            "30 days"
        ],
        "Madagascar": [
            "a",
            "90 days"
        ],
        "Maldives": [
            "a",
            "30 days"
        ],
        "Mali": [
            "f",
            ""
        ],
        "Mauritania": [
            "a",
            ""
        ],
        "Micronesia": [
            "f",
            "30 days"
        ],
        "Mozambique": [
            "a",
            "30 days"
        ],
        "Nepal": [
            "a",
            ""
        ],
        "Nigeria": [
            "f",
            ""
        ],
        "Palau": [
            "a",
            "30 days"
        ],
        "Philippines": [
            "f",
            "30 days"
        ],
        "Republic of the Congo": [
            "a",
            ""
        ],
        "Rwanda": [
            "a",
            ""
        ],
        "Saint Lucia": [
            "a",
            "6 weeks"
        ],
        "Saint Vincent and the Grenadines": [
            "f",
            "1 month"
        ],
        "Samoa": [
            "a",
            "60 days"
        ],
        "Seychelles": [
            "a",
            "1 month"
        ],
        "Singapore": [
            "f",
            "30 days"
        ],
        "Sri Lanka": [
            "e",
            "30 days"
        ],
        "Tanzania": [
            "a",
            ""
        ],
        "Timor-Leste": [
            "a",
            "30 days"
        ],
        "Togo": [
            "a",
            "7 days"
        ],
        "Tuvalu": [
            "a",
            "1 month"
        ],
        "Uganda": [
            "a",
            ""
        ],
        "Vanuatu": [
            "f",
            "30 days"
        ],
        "Zambia": [
            "a",
            "90 days"
        ]
    }
}